{
  "0A9B4653-B11E-4D6A-850E-C6FCB621626C" : {
    "objectMetadataList" : [
      [
        "0A9B4653-B11E-4D6A-850E-C6FCB621626C",
        "Root",
        "VintageGramophone",
        "geom",
        "realistic",
        "materials"
      ],
      {
        "isExpanded" : true,
        "isLocked" : false
      },
      [
        "0A9B4653-B11E-4D6A-850E-C6FCB621626C",
        "Root",
        "VintageGramophone"
      ],
      {
        "isExpanded" : true,
        "isLocked" : false
      },
      [
        "0A9B4653-B11E-4D6A-850E-C6FCB621626C",
        "Root",
        "VintageGramophone",
        "geom",
        "realistic"
      ],
      {
        "isExpanded" : true,
        "isLocked" : false
      },
      [
        "0A9B4653-B11E-4D6A-850E-C6FCB621626C",
        "Root"
      ],
      {
        "isExpanded" : true,
        "isLocked" : false
      },
      [
        "0A9B4653-B11E-4D6A-850E-C6FCB621626C",
        "Root",
        "VintageGramophone",
        "geom"
      ],
      {
        "isExpanded" : true,
        "isLocked" : false
      }
    ]
  },
  "1A8DFB8A-7CD2-461F-AAAF-09D957AE274B" : {
    "objectMetadataList" : [
      [
        "1A8DFB8A-7CD2-461F-AAAF-09D957AE274B",
        "Root"
      ],
      {
        "isExpanded" : true,
        "isLocked" : false
      }
    ]
  },
  "02E8C8E4-9274-4E8B-A53B-F20B0F343B21" : {
    "objectMetadataList" : [
      [
        "02E8C8E4-9274-4E8B-A53B-F20B0F343B21",
        "Root"
      ],
      {
        "isExpanded" : true,
        "isLocked" : false
      }
    ]
  },
  "3EB5737C-18BF-4649-93A8-1A0EC6DBE4C9" : {
    "objectMetadataList" : [
      [
        "3EB5737C-18BF-4649-93A8-1A0EC6DBE4C9",
        "Root",
        "SpatialAudio"
      ],
      {
        "isExpanded" : false,
        "isLocked" : false,
        "selectedAudioFilePrim" : {
          "string" : "\/Root\/kick_wav"
        }
      },
      [
        "3EB5737C-18BF-4649-93A8-1A0EC6DBE4C9",
        "Root"
      ],
      {
        "isExpanded" : true,
        "isLocked" : false
      },
      [
        "3EB5737C-18BF-4649-93A8-1A0EC6DBE4C9",
        "Root",
        "KickEmiter"
      ],
      {
        "isExpanded" : false,
        "isLocked" : false,
        "selectedAudioFilePrim" : {
          "string" : "\/Root\/kick_wav"
        }
      }
    ]
  },
  "65F6F990-A780-4474-B78B-572E0E4E273D" : {
    "objectMetadataList" : [
      [
        "65F6F990-A780-4474-B78B-572E0E4E273D",
        "Root"
      ],
      {
        "isExpanded" : true,
        "isLocked" : false
      }
    ]
  },
  "78B4D747-46EB-4655-A89E-CE6C203582F6" : {
    "objectMetadataList" : [
      [
        "78B4D747-46EB-4655-A89E-CE6C203582F6",
        "Root"
      ],
      {
        "isExpanded" : true,
        "isLocked" : false
      }
    ]
  },
  "1510F6C7-214D-4800-9C6C-F3964D5FC3E3" : {
    "objectMetadataList" : [
      [
        "1510F6C7-214D-4800-9C6C-F3964D5FC3E3",
        "Root"
      ],
      {
        "isExpanded" : true,
        "isLocked" : false
      }
    ]
  },
  "66168B71-AB05-424E-8B6C-D33D6E61B08F" : {
    "objectMetadataList" : [
      [
        "66168B71-AB05-424E-8B6C-D33D6E61B08F",
        "Root"
      ],
      {
        "isExpanded" : true,
        "isLocked" : false
      }
    ]
  },
  "68909BD5-79FB-443C-B900-8584A5C6F6C3" : {
    "objectMetadataList" : [
      [
        "68909BD5-79FB-443C-B900-8584A5C6F6C3",
        "Root"
      ],
      {
        "isExpanded" : true,
        "isLocked" : false
      }
    ]
  },
  "185816F3-0C52-431A-8C55-14A251778D0A" : {
    "objectMetadataList" : [
      [
        "185816F3-0C52-431A-8C55-14A251778D0A",
        "Root",
        "Sticks",
        "Stick_R",
        "geom",
        "realistic",
        "geo"
      ],
      {
        "isExpanded" : true,
        "isLocked" : false
      },
      [
        "185816F3-0C52-431A-8C55-14A251778D0A",
        "Root"
      ],
      {
        "isExpanded" : true,
        "isLocked" : false
      },
      [
        "185816F3-0C52-431A-8C55-14A251778D0A",
        "Root",
        "Stick_R"
      ],
      {
        "isExpanded" : true,
        "isLocked" : false
      },
      [
        "185816F3-0C52-431A-8C55-14A251778D0A",
        "Root",
        "Sticks",
        "Stick_R",
        "geom",
        "realistic",
        "materials"
      ],
      {
        "isExpanded" : true,
        "isLocked" : false
      },
      [
        "185816F3-0C52-431A-8C55-14A251778D0A",
        "Root",
        "Stick_L"
      ],
      {
        "isExpanded" : true,
        "isLocked" : false
      },
      [
        "185816F3-0C52-431A-8C55-14A251778D0A",
        "Root",
        "Sticks",
        "Stick_R",
        "geom",
        "realistic",
        "geo",
        "lod0"
      ],
      {
        "isExpanded" : true,
        "isLocked" : false
      },
      [
        "185816F3-0C52-431A-8C55-14A251778D0A",
        "Root",
        "Sticks",
        "Stick_R",
        "geom"
      ],
      {
        "isExpanded" : true,
        "isLocked" : false
      },
      [
        "185816F3-0C52-431A-8C55-14A251778D0A",
        "Root",
        "Sticks",
        "Stick_R",
        "geom",
        "realistic"
      ],
      {
        "isExpanded" : true,
        "isLocked" : false
      }
    ]
  },
  "475084E7-70FD-4028-9C0D-366F65BCC07C" : {
    "objectMetadataList" : [
      [
        "475084E7-70FD-4028-9C0D-366F65BCC07C",
        "Root"
      ],
      {
        "isExpanded" : true,
        "isLocked" : false
      },
      [
        "475084E7-70FD-4028-9C0D-366F65BCC07C",
        "Root",
        "Violin"
      ],
      {
        "isExpanded" : true,
        "isLocked" : false
      },
      [
        "475084E7-70FD-4028-9C0D-366F65BCC07C",
        "Root",
        "Violin",
        "geom"
      ],
      {
        "isExpanded" : true,
        "isLocked" : false
      },
      [
        "475084E7-70FD-4028-9C0D-366F65BCC07C",
        "Root",
        "Violin",
        "geom",
        "realistic"
      ],
      {
        "isExpanded" : true,
        "isLocked" : false
      }
    ]
  },
  "829713DC-4E20-4295-881D-C2F45033D3FF" : {
    "objectMetadataList" : [
      [
        "829713DC-4E20-4295-881D-C2F45033D3FF",
        "Root"
      ],
      {
        "isExpanded" : true,
        "isLocked" : false
      },
      [
        "829713DC-4E20-4295-881D-C2F45033D3FF",
        "Root",
        "Sticks",
        "Stick_L",
        "geom",
        "realistic",
        "materials"
      ],
      {
        "isExpanded" : true,
        "isLocked" : false
      },
      [
        "829713DC-4E20-4295-881D-C2F45033D3FF",
        "Root",
        "Sticks",
        "Stick_L",
        "geom"
      ],
      {
        "isExpanded" : true,
        "isLocked" : false
      },
      [
        "829713DC-4E20-4295-881D-C2F45033D3FF",
        "Root",
        "Sticks",
        "Stick_L",
        "geom",
        "realistic",
        "geo"
      ],
      {
        "isExpanded" : true,
        "isLocked" : false
      },
      [
        "829713DC-4E20-4295-881D-C2F45033D3FF",
        "Root",
        "DrumStick",
        "geom",
        "realistic",
        "materials"
      ],
      {
        "isExpanded" : true,
        "isLocked" : false
      },
      [
        "829713DC-4E20-4295-881D-C2F45033D3FF",
        "Root",
        "Sticks"
      ],
      {
        "isExpanded" : true,
        "isLocked" : false
      },
      [
        "829713DC-4E20-4295-881D-C2F45033D3FF",
        "Root",
        "Sticks",
        "Stick_L"
      ],
      {
        "isExpanded" : true,
        "isLocked" : false
      },
      [
        "829713DC-4E20-4295-881D-C2F45033D3FF",
        "Root",
        "Sticks",
        "Stick_L",
        "geom",
        "realistic"
      ],
      {
        "isExpanded" : true,
        "isLocked" : false
      }
    ]
  },
  "A8DC38D1-9EFF-4FF9-868B-711544477B61" : {
    "objectMetadataList" : [
      [
        "A8DC38D1-9EFF-4FF9-868B-711544477B61",
        "Root",
        "DrumKit"
      ],
      {
        "isExpanded" : true,
        "isLocked" : false
      },
      [
        "A8DC38D1-9EFF-4FF9-868B-711544477B61",
        "Root"
      ],
      {
        "isExpanded" : true,
        "isLocked" : false
      },
      [
        "A8DC38D1-9EFF-4FF9-868B-711544477B61",
        "Root",
        "DrumKit",
        "geom"
      ],
      {
        "isExpanded" : true,
        "isLocked" : false
      }
    ]
  },
  "A21404D0-C0FF-47E1-A891-DB5BDE9EFBEA" : {
    "objectMetadataList" : [
      [
        "A21404D0-C0FF-47E1-A891-DB5BDE9EFBEA",
        "satelite_02"
      ],
      {
        "isExpanded" : true,
        "isLocked" : false
      }
    ]
  },
  "AF09ED6F-1707-48FD-8720-65B998362C09" : {
    "objectMetadataList" : [
      [
        "AF09ED6F-1707-48FD-8720-65B998362C09",
        "Root",
        "Sphere_Right"
      ],
      {
        "isExpanded" : true,
        "isLocked" : false
      },
      [
        "AF09ED6F-1707-48FD-8720-65B998362C09",
        "Root",
        "Sphere_Left"
      ],
      {
        "isExpanded" : true,
        "isLocked" : false
      },
      [
        "AF09ED6F-1707-48FD-8720-65B998362C09",
        "Root"
      ],
      {
        "isExpanded" : true,
        "isLocked" : false
      }
    ]
  },
  "B2710F7C-DD4C-4B4E-B46A-CEA2BD350D29" : {
    "objectMetadataList" : [
      [
        "B2710F7C-DD4C-4B4E-B46A-CEA2BD350D29",
        "Root"
      ],
      {
        "isExpanded" : true,
        "isLocked" : false
      }
    ]
  },
  "CB766F92-EE55-4A63-9401-E7B8C009764D" : {
    "objectMetadataList" : [
      [
        "CB766F92-EE55-4A63-9401-E7B8C009764D",
        "Root"
      ],
      {
        "isExpanded" : true,
        "isLocked" : false
      },
      [
        "CB766F92-EE55-4A63-9401-E7B8C009764D",
        "Root",
        "GridMaterial"
      ],
      {
        "isExpanded" : true,
        "isLocked" : false
      }
    ]
  },
  "D5F689D2-4C08-4A52-8C12-586868496C53" : {
    "objectMetadataList" : [
      [
        "D5F689D2-4C08-4A52-8C12-586868496C53",
        "Root"
      ],
      {
        "isExpanded" : true,
        "isLocked" : false
      }
    ]
  },
  "D560BB77-AAF3-4BDE-B7C4-989332A4688B" : {
    "objectMetadataList" : [

    ]
  },
  "D615B912-853E-47A2-AF5D-70ED3021B5A2" : {
    "objectMetadataList" : [
      [
        "D615B912-853E-47A2-AF5D-70ED3021B5A2",
        "Root",
        "KickEmiter"
      ],
      {
        "isExpanded" : false,
        "isLocked" : false,
        "selectedAudioFilePrim" : {
          "string" : "\/Root\/kick_wav"
        }
      },
      [
        "D615B912-853E-47A2-AF5D-70ED3021B5A2",
        "Root",
        "SnareEmiter"
      ],
      {
        "isExpanded" : false,
        "isLocked" : false,
        "selectedAudioFilePrim" : {
          "string" : "\/Root\/snare_wav"
        }
      },
      [
        "D615B912-853E-47A2-AF5D-70ED3021B5A2",
        "Root"
      ],
      {
        "isExpanded" : true,
        "isLocked" : false
      },
      [
        "D615B912-853E-47A2-AF5D-70ED3021B5A2",
        "Root",
        "SnareEmitter"
      ],
      {
        "isExpanded" : false,
        "isLocked" : false,
        "selectedAudioFilePrim" : {
          "string" : "\/Root\/snare_wav"
        }
      },
      [
        "D615B912-853E-47A2-AF5D-70ED3021B5A2",
        "Root",
        "RideEmiter"
      ],
      {
        "isExpanded" : false,
        "isLocked" : false,
        "selectedAudioFilePrim" : {
          "string" : "\/Root\/crash_wav"
        }
      },
      [
        "D615B912-853E-47A2-AF5D-70ED3021B5A2",
        "Root",
        "DrumKit"
      ],
      {
        "isExpanded" : true,
        "isLocked" : false
      },
      [
        "D615B912-853E-47A2-AF5D-70ED3021B5A2",
        "Root",
        "KickEmitter"
      ],
      {
        "isExpanded" : false,
        "isLocked" : false,
        "selectedAudioFilePrim" : {
          "string" : "\/Root\/kick_wav"
        }
      },
      [
        "D615B912-853E-47A2-AF5D-70ED3021B5A2",
        "Root",
        "RideEmitter"
      ],
      {
        "isExpanded" : false,
        "isLocked" : false,
        "selectedAudioFilePrim" : {
          "string" : "\/Root\/crash_wav"
        }
      }
    ]
  },
  "D66134B1-3681-4A8E-AFE5-29F257229F3B" : {
    "objectMetadataList" : [
      [
        "D66134B1-3681-4A8E-AFE5-29F257229F3B",
        "Root",
        "gramophone",
        "Looks"
      ],
      {
        "isExpanded" : true,
        "isLocked" : false
      },
      [
        "D66134B1-3681-4A8E-AFE5-29F257229F3B",
        "Root",
        "GridMaterial",
        "GridMaterial"
      ],
      {
        "isExpanded" : true,
        "isLocked" : false
      },
      [
        "D66134B1-3681-4A8E-AFE5-29F257229F3B",
        "Root"
      ],
      {
        "isExpanded" : true,
        "isLocked" : false
      }
    ]
  },
  "DA988ECE-CB76-4352-B897-88DB543B7836" : {
    "objectMetadataList" : [
      [
        "DA988ECE-CB76-4352-B897-88DB543B7836",
        "Root"
      ],
      {
        "isExpanded" : true,
        "isLocked" : false
      }
    ]
  },
  "EB2627C7-EF96-4D37-842B-99C89C885A2E" : {
    "objectMetadataList" : [
      [
        "EB2627C7-EF96-4D37-842B-99C89C885A2E",
        "Root",
        "Satellite",
        "satellite"
      ],
      {
        "isExpanded" : true,
        "isLocked" : false
      },
      [
        "EB2627C7-EF96-4D37-842B-99C89C885A2E",
        "Root"
      ],
      {
        "isExpanded" : true,
        "isLocked" : false
      },
      [
        "EB2627C7-EF96-4D37-842B-99C89C885A2E",
        "Root",
        "Satellite",
        "Materials"
      ],
      {
        "isExpanded" : true,
        "isLocked" : false
      },
      [
        "EB2627C7-EF96-4D37-842B-99C89C885A2E",
        "Root",
        "Satellite"
      ],
      {
        "isExpanded" : true,
        "isLocked" : false
      }
    ]
  },
  "EDCFBE4C-874E-4733-9400-44A0EC220B7A" : {
    "objectMetadataList" : [
      [
        "EDCFBE4C-874E-4733-9400-44A0EC220B7A",
        "Root",
        "AcousticGuitar"
      ],
      {
        "isExpanded" : true,
        "isLocked" : false
      },
      [
        "EDCFBE4C-874E-4733-9400-44A0EC220B7A",
        "Root"
      ],
      {
        "isExpanded" : true,
        "isLocked" : false
      }
    ]
  }
}